synesthesia/__init__.py
synesthesia/gui.py
synesthesia/wsl.py
synesthesia/art_generator/__init__.py
synesthesia/art_generator/curvy_algo.py
synesthesia/art_generator/genre_colors.py
synesthesia/art_generator/lines_algo.py
synesthesia/art_generator/process_audio.py
synesthesia/art_generator/qt_canvas.py
synesthesia/art_generator/shapes_algo.py
synesthesia/art_generator/wsl.py
synesthesia/images/__init__.py
synesthesia/images/line.png
synesthesia/images/main_logo.svg
synesthesia/images/proc_img.png
synesthesia/images/title_logo.png
synesthesia_uf-0.0.95.dist-info/METADATA
synesthesia_uf-0.0.95.dist-info/WHEEL
synesthesia_uf-0.0.95.dist-info/entry_points.txt
synesthesia_uf-0.0.95.dist-info/top_level.txt
synesthesia_uf-0.0.95.dist-info/RECORD
